bats_core_pkg/__init__.py
bats_core_pkg/dist/AUTHORS
bats_core_pkg/dist/LICENSE.md
bats_core_pkg/dist/bin/bats
bats_core_pkg/dist/lib/bats-core/common.bash
bats_core_pkg/dist/lib/bats-core/formatter.bash
bats_core_pkg/dist/lib/bats-core/preprocessing.bash
bats_core_pkg/dist/lib/bats-core/semaphore.bash
bats_core_pkg/dist/lib/bats-core/test_functions.bash
bats_core_pkg/dist/lib/bats-core/tracing.bash
bats_core_pkg/dist/lib/bats-core/validator.bash
bats_core_pkg/dist/lib/bats-core/warnings.bash
bats_core_pkg/dist/libexec/bats-core/bats
bats_core_pkg/dist/libexec/bats-core/bats-exec-file
bats_core_pkg/dist/libexec/bats-core/bats-exec-suite
bats_core_pkg/dist/libexec/bats-core/bats-exec-test
bats_core_pkg/dist/libexec/bats-core/bats-format-cat
bats_core_pkg/dist/libexec/bats-core/bats-format-junit
bats_core_pkg/dist/libexec/bats-core/bats-format-pretty
bats_core_pkg/dist/libexec/bats-core/bats-format-tap
bats_core_pkg/dist/libexec/bats-core/bats-format-tap13
bats_core_pkg/dist/libexec/bats-core/bats-gather-tests
bats_core_pkg/dist/libexec/bats-core/bats-preprocess
bats_core_pkg/dist/share/man/man1/bats.1
bats_core_pkg/dist/share/man/man7/bats.7
bats_core_pkg/dist/test_helper/bats-assert/LICENSE
bats_core_pkg/dist/test_helper/bats-assert/README.md
bats_core_pkg/dist/test_helper/bats-assert/load.bash
bats_core_pkg/dist/test_helper/bats-assert/package.json
bats_core_pkg/dist/test_helper/bats-assert/src/assert.bash
bats_core_pkg/dist/test_helper/bats-assert/src/assert_equal.bash
bats_core_pkg/dist/test_helper/bats-assert/src/assert_failure.bash
bats_core_pkg/dist/test_helper/bats-assert/src/assert_line.bash
bats_core_pkg/dist/test_helper/bats-assert/src/assert_not_equal.bash
bats_core_pkg/dist/test_helper/bats-assert/src/assert_output.bash
bats_core_pkg/dist/test_helper/bats-assert/src/assert_regex.bash
bats_core_pkg/dist/test_helper/bats-assert/src/assert_success.bash
bats_core_pkg/dist/test_helper/bats-assert/src/refute.bash
bats_core_pkg-0.1.11.post1.dist-info/LICENSE.md
bats_core_pkg-0.1.11.post1.dist-info/METADATA
bats_core_pkg-0.1.11.post1.dist-info/WHEEL
bats_core_pkg-0.1.11.post1.dist-info/entry_points.txt
bats_core_pkg-0.1.11.post1.dist-info/RECORD
